constrained/__init__.py
constrained/test_constraints.py
constrained-0.0.0.dist-info/LICENSE
constrained-0.0.0.dist-info/METADATA
constrained-0.0.0.dist-info/WHEEL
constrained-0.0.0.dist-info/entry_points.txt
constrained-0.0.0.dist-info/RECORD
