Metadata-Version: 2.1
Name: constrained
Version: 0.0.0
Summary: A Python library for enforcing type, range, and lexical constraints.
Author: Jacob Valdez
Author-email: jacobfv123@gmail.com
Requires-Python: >=3.10,<4.0
Classifier: Programming Language :: Python :: 3
Classifier: Programming Language :: Python :: 3.10
Classifier: Programming Language :: Python :: 3.11
Requires-Dist: lark (>=1.1.7,<2.0.0)
